fofa_workflow/__init__.py
fofa_workflow-0.1.dist-info/METADATA
fofa_workflow-0.1.dist-info/WHEEL
fofa_workflow-0.1.dist-info/top_level.txt
fofa_workflow-0.1.dist-info/RECORD
