Metadata-Version: 2.1
Name: fofa-workflow
Version: 0.1
Summary: A fofa workflow
Home-page: https://github.com/isdkz/fofa-workflow
Author: isdkz
Author-email: dkz6174510@gmail.com
Classifier: License :: OSI Approved :: MIT License
Classifier: Programming Language :: Python :: 3
Classifier: Programming Language :: Python :: 3.7
Classifier: Programming Language :: Python :: 3.8
Classifier: Programming Language :: Python :: 3.9
Requires-Python: >=3.7
Requires-Dist: requests
